{"name":"MaciejZiolkowski","tagline":"Maciej Ziolkowski Blockchain Bitcoin - Maciek Ziolkowski - Warsaw Poland - Satoshi.pl","body":"Maciej Ziolkowski Blockchain Bitcoin - Maciek Ziolkowski - Warsaw Poland - Satoshi.pl\r\n\r\nMaciej Ziółkowski - założył pierwszego w Polsce bloga o tematyce Bitcoin - Satoshi.pl. Maciej jest absolwentem Finansów i Rachunkowości na Uniwersytecie Mikołaja Kopernika w Toruniu. Zorganizował pierwsze polskie konferencje dotyczące tematyki “Social Lending” w roku 2011 i ponownie w 2012 a następnie o Bitcoin w 2013. Maciek Ziółkowski prowadzi badania nad rozwojem płatności internetowych i cyfrowych walut - w tym głównie Bitcoin, Namecoin oraz technologii Blockchain. Maciej jest współorganizatorem regularnych spotkań o tematyce BTC. https://www.youtube.com/watch?v=eWZIiFq-_q8\r\n\r\nMaciej Ziółkowski is a member of KASE – Club of Austrian Economics in Poland, KoLiber and guest speaker for ESFL and various economics conferences – about finance, social lending and Bitcoin. Maciej has a bachelor degree in Finance and Accounting from Nicolaus Copernicus University in Torun, Poland.\r\n\r\nMaciej Ziolkowski is creator of one of the first in the world News Sources about Blockchain Technology and author of first polish blog about Bitcoin - Satoshi.pl. Organizer of first Social Lending / Peer-to-peer lending conference in Poland and one of the earliest Bitcoin events in Europe. Speaker on various Virtual Currencies Seminars – London, Berlin, Prague, Warsaw. Author of many Bitcoin publications and co-author of Bitcoin realated materials and Wikipedia Virtual Currencies articles.","google":"","note":"Don't delete this file! It's used internally to help with page regeneration."}